mat3ra/__init__.py
mat3ra/utils/__init__.py
mat3ra/utils/array.py
mat3ra/utils/assertion.py
mat3ra/utils/command.py
mat3ra/utils/factory.py
mat3ra/utils/file.py
mat3ra/utils/matrix.py
mat3ra/utils/mixins.py
mat3ra/utils/object.py
mat3ra/utils/regex.py
mat3ra/utils/search.py
mat3ra/utils/string.py
mat3ra/utils/url.py
mat3ra/utils/uuid.py
mat3ra/utils/extra/__init__.py
mat3ra/utils/extra/jinja.py
mat3ra/utils/extra/tabulate.py
mat3ra/utils/jupyterlite/__init__.py
mat3ra/utils/jupyterlite/enums.py
mat3ra/utils/jupyterlite/environment.py
mat3ra/utils/jupyterlite/io.py
mat3ra/utils/jupyterlite/logger.py
mat3ra/utils/jupyterlite/packages.py
mat3ra/utils/jupyterlite/plot.py
mat3ra/utils/jupyterlite/settings.py
mat3ra/utils/jupyterlite/url.py
mat3ra/utils/scripts/__init__.py
mat3ra/utils/scripts/wheel_server.py
mat3ra_utils-2025.12.22.post0.dist-info/licenses/LICENSE.md
mat3ra_utils-2025.12.22.post0.dist-info/METADATA
mat3ra_utils-2025.12.22.post0.dist-info/WHEEL
mat3ra_utils-2025.12.22.post0.dist-info/entry_points.txt
mat3ra_utils-2025.12.22.post0.dist-info/top_level.txt
mat3ra_utils-2025.12.22.post0.dist-info/RECORD
