Metadata-Version: 2.4
Name: mat3ra-utils
Version: 2025.12.22.post0
Summary: Utils.
Author-email: "Exabyte Inc." <info@mat3ra.com>
License: # LICENSE
Classifier: Programming Language :: Python
Classifier: Programming Language :: Python :: 3
Classifier: Development Status :: 3 - Alpha
Classifier: Topic :: Software Development
Requires-Python: >=3.8
License-File: LICENSE.md
Requires-Dist: numpy
Provides-Extra: extra
Requires-Dist: tabulate; extra == "extra"
Requires-Dist: jinja2; extra == "extra"
Provides-Extra: jupyterlite
Requires-Dist: pyyaml; extra == "jupyterlite"
Requires-Dist: matplotlib>=3.4.1; extra == "jupyterlite"
Requires-Dist: plotly>=5.18; extra == "jupyterlite"
Requires-Dist: ipython>=8.0; extra == "jupyterlite"
Provides-Extra: dev
Requires-Dist: pre-commit; extra == "dev"
Requires-Dist: black; extra == "dev"
Requires-Dist: ruff; extra == "dev"
Requires-Dist: isort; extra == "dev"
Requires-Dist: mypy; extra == "dev"
Requires-Dist: pip-tools; extra == "dev"
Provides-Extra: tests
Requires-Dist: coverage[toml]>=5.3; extra == "tests"
Requires-Dist: pytest; extra == "tests"
Requires-Dist: pytest-cov; extra == "tests"
Requires-Dist: pytest-mock; extra == "tests"
Requires-Dist: gradio; extra == "tests"
Requires-Dist: pydantic; extra == "tests"
Requires-Dist: mat3ra-utils[extra]; extra == "tests"
Provides-Extra: all
Requires-Dist: mat3ra-utils[tests]; extra == "all"
Requires-Dist: mat3ra-utils[dev]; extra == "all"
Dynamic: license-file
